opengood/__init__.py
opengood/py_ml_plot/__init__.py
opengood/py_ml_plot/classification_plot.py
opengood_py_ml_plot-2.3.0.dist-info/licenses/LICENSE
opengood_py_ml_plot-2.3.0.dist-info/METADATA
opengood_py_ml_plot-2.3.0.dist-info/WHEEL
opengood_py_ml_plot-2.3.0.dist-info/top_level.txt
opengood_py_ml_plot-2.3.0.dist-info/RECORD
