Metadata-Version: 2.4
Name: opengood.py_ml_plot
Version: 2.3.0
Summary: Modules containing reusable functions for machine learning visualization plotting
Author-email: OpenGood <ai@opengood.ai>
License: MIT License
Project-URL: Homepage, https://github.com/opengood-aio/py-ml-plot
Project-URL: Documentation, https://github.com/opengood-aio/py-ml-plot
Classifier: Programming Language :: Python :: 3
Classifier: License :: OSI Approved :: MIT License
Classifier: Operating System :: OS Independent
Requires-Python: >=3.12
License-File: LICENSE
Requires-Dist: matplotlib>=3.10.3
Requires-Dist: numpy>=2.3.0rc1
Requires-Dist: pandas>=2.2.3
Requires-Dist: scikit-learn>=1.7.0rc1
Dynamic: license-file
